nginxsitepy/__init__.py
nginxsitepy/console.py
nginxsitepy-0.1.0.dist-info/METADATA
nginxsitepy-0.1.0.dist-info/WHEEL
nginxsitepy-0.1.0.dist-info/entry_points.txt
nginxsitepy-0.1.0.dist-info/RECORD
